pdf2xlsx/__init__.py
pdf2xlsx/__main__.py
pdf2xlsx/config.py
pdf2xlsx/gui.py
pdf2xlsx/invoice.py
pdf2xlsx/logger.py
pdf2xlsx/managment.py
pdf2xlsx/order_detail_xlsx_parse.py
pdf2xlsx/utility.py
pdf2xlsx-1.1.5.dist-info/DESCRIPTION.rst
pdf2xlsx-1.1.5.dist-info/METADATA
pdf2xlsx-1.1.5.dist-info/RECORD
pdf2xlsx-1.1.5.dist-info/WHEEL
pdf2xlsx-1.1.5.dist-info/metadata.json
pdf2xlsx-1.1.5.dist-info/top_level.txt
